scamp/__init__.py
scamp/_dependencies.py
scamp/_engraving_translations.py
scamp/_metric_structure.py
scamp/_midi.py
scamp/_parsing.py
scamp/_soundfont_host.py
scamp/instruments.py
scamp/note_properties.py
scamp/performance.py
scamp/playback_adjustments.py
scamp/playback_implementations.py
scamp/quantization.py
scamp/score.py
scamp/session.py
scamp/settings.py
scamp/simple.py
scamp/spanners.py
scamp/spelling.py
scamp/test_run.py
scamp/text.py
scamp/transcriber.py
scamp/utilities.py
scamp/__pyinstaller/__init__.py
scamp/__pyinstaller/hook-scamp.py
scamp/_thirdparty/__init__.py
scamp/_thirdparty/fluidsynth.py
scamp/_thirdparty/mac_libs/libFLAC.8.dylib
scamp/_thirdparty/mac_libs/libfluidsynth.3.0.1.dylib
scamp/_thirdparty/mac_libs/libglib-2.0.0.dylib
scamp/_thirdparty/mac_libs/libgthread-2.0.0.dylib
scamp/_thirdparty/mac_libs/libintl.8.dylib
scamp/_thirdparty/mac_libs/libogg.0.dylib
scamp/_thirdparty/mac_libs/libopus.0.dylib
scamp/_thirdparty/mac_libs/libpcre.1.dylib
scamp/_thirdparty/mac_libs/libportaudio.2.dylib
scamp/_thirdparty/mac_libs/libreadline.8.dylib
scamp/_thirdparty/mac_libs/libsndfile.1.dylib
scamp/_thirdparty/mac_libs/libvorbis.0.dylib
scamp/_thirdparty/mac_libs/libvorbisenc.2.dylib
scamp/_thirdparty/sf2or3utils/__init__.py
scamp/_thirdparty/sf2or3utils/bag.py
scamp/_thirdparty/sf2or3utils/generator.py
scamp/_thirdparty/sf2or3utils/instrument.py
scamp/_thirdparty/sf2or3utils/modulator.py
scamp/_thirdparty/sf2or3utils/preset.py
scamp/_thirdparty/sf2or3utils/riffparser.py
scamp/_thirdparty/sf2or3utils/sample.py
scamp/_thirdparty/sf2or3utils/sf2parse.py
scamp/_thirdparty/sf2or3utils/tests/__init__.py
scamp/_thirdparty/sf2or3utils/tests/test_parse.py
scamp/_thirdparty/windows_libs/libfluidsynth.dll
scamp/_thirdparty/windows_libs/libfluidsynth64.dll
scamp/lilypond/scamp_template.ly
scamp/soundfonts/Merlin.sf2
scamp-0.9.2.post2.dist-info/LICENSE.txt
scamp-0.9.2.post2.dist-info/METADATA
scamp-0.9.2.post2.dist-info/WHEEL
scamp-0.9.2.post2.dist-info/entry_points.txt
scamp-0.9.2.post2.dist-info/top_level.txt
scamp-0.9.2.post2.dist-info/RECORD
