Metadata-Version: 2.1
Name: scamp
Version: 0.9.2.post2
Summary: A computer-assisted composition framework that manages the flow of musical time, plays back notes via SoundFonts, MIDI or OSC, and quantizes and saves the result to music notation.
Home-page: http://scamp.marcevanstein.com
Author: Marc Evanstein
Author-email: marc@marcevanstein.com
License: GNU GPL Version 3
Project-URL: Source Code, https://sr.ht/~marcevanstein/scamp/
Project-URL: Documentation, http://scamp.marcevanstein.com/
Project-URL: Forum, http://scampsters.marcevanstein.com/
Platform: UNKNOWN
Classifier: Programming Language :: Python :: 3.10
Classifier: License :: OSI Approved :: GNU General Public License v3 (GPLv3)
Classifier: Operating System :: OS Independent
Requires-Python: >=3.10
License-File: LICENSE.txt
Requires-Dist: arpeggio
Requires-Dist: clockblocks (>=0.6.9)
Requires-Dist: expenvelope (>=0.7.2)
Requires-Dist: midiutil
Requires-Dist: pymusicxml (>=0.5.6)
Requires-Dist: python-osc
Provides-Extra: all
Requires-Dist: abjad (<=3.19,>=3.17) ; extra == 'all'
Requires-Dist: pynput ; extra == 'all'
Requires-Dist: python-rtmidi ; extra == 'all'
